MANIFEST.in
README.rst
setup.py
sshed/__init__.py
sshed/argparse_actions.py
sshed/commands.py
sshed/exceptions.py
sshed.egg-info/PKG-INFO
sshed.egg-info/SOURCES.txt
sshed.egg-info/dependency_links.txt
sshed.egg-info/requires.txt
sshed.egg-info/top_level.txt
sshed/servers/__init__.py
sshed/servers/base.py
sshed/servers/centos.py
sshed/servers/configure.py