Metadata-Version: 1.1
Name: sshed
Version: 0.3.0
Summary: Minimal Parmaiko/ssh2 wrapper to make working with SSH easy.
Home-page: http://cwood.github.com/sshed/
Author: Colin Wood
Author-email: cwood06@gmail.com
License: UNKNOWN
Download-URL: http://github.com/cwood/sshed/tarball/master
Keywords: ssh,automation,remote,ssh2,OpenSSH
Platform: UNKNOWN
Classifier: Development Status :: 4 - Beta
Classifier: Environment :: Console
Classifier: Intended Audience :: Developers
Classifier: Intended Audience :: Information Technology
Classifier: Intended Audience :: System Administrators
Classifier: License :: OSI Approved :: GNU General Public License v2 or later (GPLv2+)
Classifier: Operating System :: POSIX
Classifier: Programming Language :: Python :: 2.5
Classifier: Programming Language :: Python :: 2.6
Classifier: Programming Language :: Python :: 2.7
Classifier: Topic :: System :: Networking
Classifier: Topic :: System :: Systems Administration
